{
  "$schema_version": 1,
  "user": {
    "name": "Erik",
    "start_date": "2026-04-28",
    "phase": "1 \u2014 Base + shoulder",
    "phase_window": "May \u2192 mid-July 2026"
  },
  "current_week_overrides": {},
  "log": [
    {
      "date": "2026-04-28",
      "planned": "Strength A",
      "did": "Strength A; tested TGU at 20 lb \u2014 too heavy, dropping back to 17.5",
      "shoulder_during": "green",
      "shoulder_post_24h": "green",
      "sleep_side_tolerance": null,
      "notes": "Post-workout ~3/10 anterior + superior left shoulder \u2014 confirmed average / baseline (not a flare). 20 lb TGU test failed; hold at 17.5, retest in 2 weeks. AM next-day check: 0\u20131/10, much better.",
      "processed_memos": [
        "coach-20260428-2121.json",
        "coach-20260429-0756.json"
      ]
    },
    {
      "date": "2026-04-29",
      "planned": "Run \u2014 hilly zone 2",
      "did": "5.4 mi run in 50 min (\u22489:15/mi pace)",
      "shoulder_during": "green",
      "shoulder_post_24h": "green",
      "sleep_side_tolerance": null,
      "notes": "1/10 anterior shoulder burning during run, very mild. AM next-day check (4/30): 1/10, felt good overall.",
      "processed_memos": [
        "coach-20260429-1219.json",
        "coach-20260430-2141.json"
      ]
    },
    {
      "date": "2026-04-30",
      "planned": "Strength B",
      "did": "Strength B as prescribed. Prone Y-T-W @ 5 lb DBs; Cossack squat @ 17.5 lb KB; ATG/Bulgarian split squat @ 15 lb KB; single-leg RDL @ 17.5 lb KB.",
      "shoulder_during": "green",
      "shoulder_post_24h": "green",
      "sleep_side_tolerance": null,
      "notes": "Loads above week-1 prescription on Cossack (17.5 KB vs BW) and split squat (15 KB vs BW); single-leg RDL 17.5 vs prescribed 20. Workout went well. AM next-day check (5/1): zero pain.",
      "processed_memos": [
        "coach-20260430-2141.json",
        "coach-20260501-0705.json"
      ]
    }
  ],
  "garmin": {
    "last_synced": "2026-05-01",
    "recent_activities": [
      {
        "date": "2026-04-29",
        "type": "Trail run",
        "detail": "5.3 mi \u00b7 49:41 \u00b7 avg HR 156",
        "raw_type": "trail_running",
        "elevation_gain_m": 184.34000000357628,
        "training_load": 174.64016723632812
      },
      {
        "date": "2026-04-21",
        "type": "Trail run",
        "detail": "4.4 mi \u00b7 42:13 \u00b7 avg HR 150",
        "raw_type": "trail_running",
        "elevation_gain_m": 185.5600000023842,
        "training_load": 131.85662841796875
      },
      {
        "date": "2026-04-20",
        "type": "Climb",
        "detail": "59:56 \u00b7 avg HR 123",
        "raw_type": "indoor_climbing",
        "elevation_gain_m": 96.01999999955297,
        "training_load": 49.852783203125
      }
    ],
    "recent_sleep": [],
    "recent_resting_hr": [
      {
        "date": "2026-04-29",
        "bpm": 129
      },
      {
        "date": "2026-04-21",
        "bpm": 148
      },
      {
        "date": "2026-04-20",
        "bpm": 109
      }
    ]
  },
  "open_questions": [],
  "daily_briefs": {
    "2026-05-01": {
      "why_today": "Friday sits between yesterday's Strength B and tomorrow's Long Day \u2014 the lightest slot of the week, by design. Today is a deliberate offload, not a missed session.",
      "evidence": "Polarized training research (Seiler, Foster) consistently shows that low-intensity recovery days protect the quality of hard days; cutting them out reduces output on the workouts that actually drive adaptation, and ACWR drift into the injury-risk band starts when tissue load piles up without these valves.",
      "building_toward": "Phase 1 base + shoulder. Mobility today keeps the runner anti-tightening work and the PT shoulder staples (band ER, foam roller t-spine) in weekly rotation without adding load \u2014 small deposits, big interest by mid-July.",
      "modification": null
    },
    "2026-05-02": {
      "why_today": "Saturday is the long-day slot \u2014 your highest-volume session of the week, placed after Friday's offload so you come in fresh. Week A means a long hilly hike.",
      "evidence": "Extended low-intensity work (2\u20134 hr, conversational pace) builds aerobic base and connective-tissue durability without the eccentric stress that climbing and strength days impose on the shoulder. The progressive pack loading (bodyweight \u2192 25 lb over weeks) adds capacity without spiking ACWR.",
      "building_toward": "Aerobic floor for the December marathon goal and general climbing endurance. Once 4 weeks pass symptom-free, Week B (tension board + easy run) becomes the default and you move to 2\u00d7 climbing/wk \u2014 the hike weeks are earning that transition.",
      "modification": null
    }
  }
}
